{"from_date":"2026-05-21","to_date":"2026-06-30","generated_at":"2026-06-29T04:22:43.031180+00:00","rows_count":43,"columns":["WorkDate","InTime","OutTime","TotalWorkTime","Status"],"rows":[{"WorkDate":"2026-05-21","InTime":"06:59:00","OutTime":"15:30:00","TotalWorkTime":"08:31","Status":"دخول/خروج"},{"WorkDate":"2026-05-22","InTime":null,"OutTime":null,"TotalWorkTime":null,"Status":"جمعة"},{"WorkDate":"2026-05-23","InTime":"07:00:00","OutTime":"15:30:00","TotalWorkTime":"08:30","Status":"دخول/خروج"},{"WorkDate":"2026-05-24","InTime":"07:00:00","OutTime":"15:30:00","TotalWorkTime":"08:30","Status":"دخول/خروج"},{"WorkDate":"2026-05-25","InTime":"06:59:00","OutTime":"15:30:00","TotalWorkTime":"08:31","Status":"دخول/خروج"},{"WorkDate":"2026-05-26","InTime":"06:59:00","OutTime":"11:09:00","TotalWorkTime":"04:10","Status":"دخول/خروج"},{"WorkDate":"2026-05-26","InTime":"07:00:00","OutTime":"11:20:00","TotalWorkTime":"04:20","Status":"إجازة برمجية ساعية"},{"WorkDate":"2026-05-27","InTime":null,"OutTime":null,"TotalWorkTime":null,"Status":"عطلة رسمية"},{"WorkDate":"2026-05-28","InTime":null,"OutTime":null,"TotalWorkTime":null,"Status":"عطلة رسمية"},{"WorkDate":"2026-05-29","InTime":null,"OutTime":null,"TotalWorkTime":null,"Status":"جمعة"},{"WorkDate":"2026-05-30","InTime":null,"OutTime":null,"TotalWorkTime":null,"Status":"عطلة رسمية"},{"WorkDate":"2026-05-31","InTime":"06:58:00","OutTime":"15:30:00","TotalWorkTime":"08:32","Status":"دخول/خروج"},{"WorkDate":"2026-06-01","InTime":"06:58:00","OutTime":"15:30:00","TotalWorkTime":"08:32","Status":"دخول/خروج"},{"WorkDate":"2026-06-02","InTime":"06:59:00","OutTime":"15:30:00","TotalWorkTime":"08:31","Status":"دخول/خروج"},{"WorkDate":"2026-06-03","InTime":"06:57:00","OutTime":"15:30:00","TotalWorkTime":"08:33","Status":"دخول/خروج"},{"WorkDate":"2026-06-04","InTime":"07:00:00","OutTime":"15:30:00","TotalWorkTime":"08:30","Status":"دخول/خروج"},{"WorkDate":"2026-06-05","InTime":null,"OutTime":null,"TotalWorkTime":null,"Status":"جمعة"},{"WorkDate":"2026-06-06","InTime":"06:57:00","OutTime":"15:30:00","TotalWorkTime":"08:33","Status":"دخول/خروج"},{"WorkDate":"2026-06-07","InTime":null,"OutTime":null,"TotalWorkTime":null,"Status":"إجازة  سنوية"},{"WorkDate":"2026-06-08","InTime":"06:57:00","OutTime":"15:30:00","TotalWorkTime":"08:33","Status":"دخول/خروج"},{"WorkDate":"2026-06-09","InTime":"06:58:00","OutTime":"15:30:00","TotalWorkTime":"08:32","Status":"دخول/خروج"},{"WorkDate":"2026-06-10","InTime":"06:59:00","OutTime":"15:30:00","TotalWorkTime":"08:31","Status":"دخول/خروج"},{"WorkDate":"2026-06-11","InTime":"07:00:00","OutTime":"13:02:00","TotalWorkTime":"06:02","Status":"إجازة برمجية ساعية"},{"WorkDate":"2026-06-11","InTime":"06:57:00","OutTime":"09:25:00","TotalWorkTime":"02:28","Status":"دخول/خروج"},{"WorkDate":"2026-06-12","InTime":null,"OutTime":null,"TotalWorkTime":null,"Status":"جمعة"},{"WorkDate":"2026-06-13","InTime":"07:00:00","OutTime":"15:30:00","TotalWorkTime":"08:30","Status":"دخول/خروج"},{"WorkDate":"2026-06-14","InTime":"06:58:00","OutTime":"15:30:00","TotalWorkTime":"08:32","Status":"دخول/خروج"},{"WorkDate":"2026-06-15","InTime":"07:00:00","OutTime":"15:30:00","TotalWorkTime":"08:30","Status":"دخول/خروج"},{"WorkDate":"2026-06-16","InTime":"06:56:00","OutTime":"15:30:00","TotalWorkTime":"08:34","Status":"عطلة رسمية"},{"WorkDate":"2026-06-17","InTime":"06:58:00","OutTime":"15:30:00","TotalWorkTime":"08:32","Status":"دخول/خروج"},{"WorkDate":"2026-06-18","InTime":"06:59:00","OutTime":"15:30:00","TotalWorkTime":"08:31","Status":"دخول/خروج"},{"WorkDate":"2026-06-19","InTime":null,"OutTime":null,"TotalWorkTime":null,"Status":"جمعة"},{"WorkDate":"2026-06-20","InTime":"06:58:00","OutTime":"15:30:00","TotalWorkTime":"08:32","Status":"دخول/خروج"},{"WorkDate":"2026-06-21","InTime":"07:00:00","OutTime":"15:30:00","TotalWorkTime":"08:30","Status":"دخول/خروج"},{"WorkDate":"2026-06-22","InTime":null,"OutTime":null,"TotalWorkTime":null,"Status":"غياب غير مبرر"},{"WorkDate":"2026-06-23","InTime":"06:59:00","OutTime":"10:22:00","TotalWorkTime":"03:23","Status":"دخول/خروج"},{"WorkDate":"2026-06-24","InTime":"06:58:00","OutTime":"10:36:00","TotalWorkTime":"03:38","Status":"دخول/خروج"},{"WorkDate":"2026-06-25","InTime":"07:04:00","OutTime":"15:20:00","TotalWorkTime":"08:16","Status":"دخول/خروج"},{"WorkDate":"2026-06-26","InTime":null,"OutTime":null,"TotalWorkTime":null,"Status":"جمعة"},{"WorkDate":"2026-06-27","InTime":"06:58:00","OutTime":"15:20:00","TotalWorkTime":"08:22","Status":"دخول/خروج"},{"WorkDate":"2026-06-28","InTime":"06:58:00","OutTime":null,"TotalWorkTime":null,"Status":"دخول/خروج"},{"WorkDate":"2026-06-29","InTime":null,"OutTime":null,"TotalWorkTime":null,"Status":null},{"WorkDate":"2026-06-30","InTime":null,"OutTime":null,"TotalWorkTime":null,"Status":null}]}